README.md
setup.py
BackpackTF/__init__.py
BackpackTF/account.py
BackpackTF/currency.py
BackpackTF/miscutils.py
BackpackTF.egg-info/PKG-INFO
BackpackTF.egg-info/SOURCES.txt
BackpackTF.egg-info/dependency_links.txt
BackpackTF.egg-info/requires.txt
BackpackTF.egg-info/top_level.txt