Metadata-Version: 2.1
Name: BackpackTF
Version: 0.1.1
Summary: The Unoffical Backpack.tf API Wrapper in Python 3.
Home-page: https://github.com/davidteather/BackpackTf-API
Author: David Teather
Author-email: contact.davidteather@gmail.com
License: MIT
Download-URL: https://github.com/davidteather/BackpackTf-API/tarball/master
Keywords: backpacktf,python3,tf2,unofficial,backpack.tf,trading-bot,api
Platform: UNKNOWN
Classifier: Development Status :: 3 - Alpha
Classifier: Intended Audience :: Developers
Classifier: Topic :: Software Development :: Build Tools
Classifier: License :: OSI Approved :: MIT License
Classifier: Programming Language :: Python :: 3.7
Classifier: Programming Language :: Python :: 3.6
Classifier: Programming Language :: Python :: 3.5
Classifier: Programming Language :: Python :: 3.4
